IP_Design/timer.v
module timer #(
	parameter WIDTH = 8 
)( 
	input wire clk ,
	input wire rst ,
	input wire start ,
	input wire [WIDTH-1:0] load_Val ,
	output reg done 
);
	
	reg [WIDTH-1:0] count ;
	reg running ;

	always @( posedge clk or posedge rst) begin 
		if(rst) begin 
			count <= 0 ;
			running <= 0 ;
			done <= 0 ;
		end
		else begin
			if (start) begin
				count <= load_Val ;
				running <= 1 ;
				done <= 0 ;
			end
			else if (running) begin
				if(count > 0) begin
					count <= count -1 ;
				end else begin
					running <= 0 ;
					done <= 1 ;
				end
			end
		end
	end
endmodule

IP_Design/timer_tb.v
`timescale 1ns/1ps

module timer_tb ;
	
	reg clk = 0 ;
	reg rst = 1 ;
	reg start = 0 ;
	reg [7:0] load_Val = 0 ; 
	wire done ;

	timer #(.WIDTH(8)) dut (
		.clk(clk),
		.rst(rst),
		.start(start),
		.load_Val(load_Val),
		.done(done)
	);

	always #5 clk = ~clk ;

	initial begin
		$dumpfile("Timer.vcd");
		$dumpvars(0,timer_tb);

		#10 rst = 0 ;

		#5 load_Val = 8'd5 ; start = 1 ;
		
		#10 start = 0 ;

		#100 ; 

		#5 load_Val = 8'd3 ; start = 1 ;

		#10 start = 0 ;

		#50 $finish ;
	end
endmodule

IP_Design/Timer.vcd
$date
	Wed Feb 18 12:04:31 2026
$end
$version
	Icarus Verilog
$end
$timescale
	1ps
$end
$scope module timer_tb $end
$var wire 1 ! done $end
$var reg 1 " clk $end
$var reg 8 # load_Val [7:0] $end
$var reg 1 $ rst $end
$var reg 1 % start $end
$scope module dut $end
$var wire 1 " clk $end
$var wire 8 & load_Val [7:0] $end
$var wire 1 $ rst $end
$var wire 1 % start $end
$var reg 8 ' count [7:0] $end
$var reg 1 ! done $end
$var reg 1 ( running $end
$upscope $end
$upscope $end
$enddefinitions $end
#0
$dumpvars
0(
b0 '
b0 &
0%
1$
b0 #
0"
0!
$end
#5000
1"
#10000
0"
0$
#15000
1(
b101 '
1"
1%
b101 #
b101 &
#20000
0"
#25000
b100 '
1"
0%
#30000
0"
#35000
b11 '
1"
#40000
0"
#45000
b10 '
1"
#50000
0"
#55000
b1 '
1"
#60000
0"
#65000
b0 '
1"
#70000
0"
#75000
1!
0(
1"
#80000
0"
#85000
1"
#90000
0"
#95000
1"
#100000
0"
#105000
1"
#110000
0"
#115000
1"
#120000
0"
#125000
1"
#130000
0"
1%
b11 #
b11 &
#135000
0!
1(
b11 '
1"
#140000
0"
0%
#145000
b10 '
1"
#150000
0"
#155000
b1 '
1"
#160000
0"
#165000
b0 '
1"
#170000
0"
#175000
1!
0(
1"
