Multiple_IP/mux.v
module mux (
	input [1:0] in0 , in1 ,
	input sel ,
	output [1:0] out
);

	assign out = sel ? in0 : in1 ;
	
endmodule

Multiple_IP/alu.v
module alu (
	input [1:0] a , 
	input [1:0] b ,
	input sel ,
	output reg [1:0] result
);

	always @(*) begin 
		case (sel)
			1'b0 : result = a + b ;
			1'b1 : result = a - b ;
		endcase
	end
endmodule

Multiple_IP/counter.v
module counter (
	input clk , rst ,
	output reg [3:0] count 
);

	always @(posedge clk) begin
		if (rst) 
			count <= 0  ;
		else
			count <= count + 1 ;
	end
endmodule

Multiple_IP/mini_soc.v
module mini_soc (
	input clk , rst , alu_sel , mux_sel ,
	output [1:0] soc_out 
);
	wire [3:0] count ;
	wire [1:0] alu_out;

	counter u_counter (.clk(clk), .rst(rst) , .count(count) );
	alu u_alu (.a(count[3:2]) , .b(count[1:0]) , .sel(alu_sel) , .result(alu_out));
	mux u_mux(.in0(count[3:2]), .in1(alu_out) , .sel(mux_sel) , .out(soc_out));
	
endmodule

Multiple_IP/mini_soc_tb.v
module mini_soc_tb;

    reg clk = 0;
    reg rst = 1;
    reg alu_sel = 0;
    reg mux_sel = 0;

    wire [1:0] soc_out;

    // Clock generation: 10 time unit period
    always #5 clk = ~clk;

    // DUT instantiation
    mini_soc dut (
        .clk     (clk),
        .rst     (rst),
        .alu_sel (alu_sel),
        .mux_sel (mux_sel),
        .soc_out (soc_out)
    );

    initial begin
        // Dump waveform
        $dumpfile("dump.vcd");
        $dumpvars(0, mini_soc_tb);

        // Reset release
        #10 rst = 0;

        // Stimulate ALU and MUX selections
        #20 alu_sel = 1;
        #30 mux_sel = 1;
        #40 alu_sel = 0;
        #20 mux_sel = 0;

        #50 $finish;
    end

endmodule

Multiple_IP/dump.vcd
$date
	Wed Feb 18 12:37:00 2026
$end
$version
	Icarus Verilog
$end
$timescale
	1s
$end
$scope module mini_soc_tb $end
$var wire 2 ! soc_out [1:0] $end
$var reg 1 " alu_sel $end
$var reg 1 # clk $end
$var reg 1 $ mux_sel $end
$var reg 1 % rst $end
$scope module dut $end
$var wire 1 " alu_sel $end
$var wire 1 # clk $end
$var wire 1 $ mux_sel $end
$var wire 1 % rst $end
$var wire 2 & soc_out [1:0] $end
$var wire 4 ' count [3:0] $end
$var wire 2 ( alu_out [1:0] $end
$scope module u_alu $end
$var wire 2 ) a [1:0] $end
$var wire 2 * b [1:0] $end
$var wire 1 " sel $end
$var reg 2 + result [1:0] $end
$upscope $end
$scope module u_counter $end
$var wire 1 # clk $end
$var wire 1 % rst $end
$var reg 4 , count [3:0] $end
$upscope $end
$scope module u_mux $end
$var wire 2 - in0 [1:0] $end
$var wire 2 . in1 [1:0] $end
$var wire 1 $ sel $end
$var wire 2 / out [1:0] $end
$upscope $end
$upscope $end
$upscope $end
$enddefinitions $end
#0
$dumpvars
bx /
bx .
bx -
bx ,
bx +
bx *
bx )
bx (
bx '
bx &
1%
0$
0#
0"
bx !
$end
#5
b0 !
b0 &
b0 /
b0 (
b0 +
b0 .
b0 -
b0 *
b0 )
b0 '
b0 ,
1#
#10
0#
0%
#15
b1 !
b1 &
b1 /
b1 (
b1 +
b1 .
b1 *
b1 '
b1 ,
1#
#20
0#
#25
b10 !
b10 &
b10 /
b10 (
b10 +
b10 .
b10 *
b10 '
b10 ,
1#
#30
0#
1"
#35
b1 !
b1 &
b1 /
b1 (
b1 +
b1 .
b11 *
b11 '
b11 ,
1#
#40
0#
#45
b1 -
b0 *
b1 )
b100 '
b100 ,
1#
#50
0#
#55
b0 !
b0 &
b0 /
b0 (
b0 +
b0 .
b1 *
b101 '
b101 ,
1#
#60
b1 !
b1 &
b1 /
0#
1$
#65
b11 (
b11 +
b11 .
b10 *
b110 '
b110 ,
1#
#70
0#
#75
b10 (
b10 +
b10 .
b11 *
b111 '
b111 ,
1#
#80
0#
#85
b10 !
b10 &
b10 /
b10 -
b0 *
b10 )
b1000 '
b1000 ,
1#
#90
0#
#95
b1 (
b1 +
b1 .
b1 *
b1001 '
b1001 ,
1#
#100
b11 (
b11 +
b11 .
0#
0"
#105
b0 (
b0 +
b0 .
b10 *
b1010 '
b1010 ,
1#
#110
0#
#115
b1 (
b1 +
b1 .
b11 *
b1011 '
b1011 ,
1#
#120
b1 !
b1 &
b1 /
0#
0$
#125
b11 !
b11 &
b11 /
b11 (
b11 +
b11 .
b11 -
b0 *
b11 )
b1100 '
b1100 ,
1#
#130
0#
#135
b0 !
b0 &
b0 /
b0 (
b0 +
b0 .
b1 *
b1101 '
b1101 ,
1#
#140
0#
#145
b1 !
b1 &
b1 /
b1 (
b1 +
b1 .
b10 *
b1110 '
b1110 ,
1#
#150
0#
#155
b10 !
b10 &
b10 /
b10 (
b10 +
b10 .
b11 *
b1111 '
b1111 ,
1#
#160
0#
#165
b0 !
b0 &
b0 /
b0 (
b0 +
b0 .
b0 -
b0 *
b0 )
b0 '
b0 ,
1#
